intentai/__init__.py
intentai/cli.py
intentai/core.py
intentai/decorator.py
intentai/detector.py
intentai/types.py
intentai-1.0.0.dist-info/METADATA
intentai-1.0.0.dist-info/WHEEL
intentai-1.0.0.dist-info/entry_points.txt
intentai-1.0.0.dist-info/licenses/LICENSE
intentai-1.0.0.dist-info/RECORD
