Metadata-Version: 2.4
Name: intentai
Version: 1.0.0
Summary: Dynamic tool detection and parameter extraction system that converts natural language into structured tool calls
Project-URL: Homepage, https://github.com/your-username/intentai
Project-URL: Documentation, https://intentai.readthedocs.io/
Project-URL: Repository, https://github.com/your-username/intentai
Project-URL: Bug Tracker, https://github.com/your-username/intentai/issues
Project-URL: Source Code, https://github.com/your-username/intentai
Project-URL: Download, https://pypi.org/project/intentai/#files
Project-URL: Changelog, https://github.com/your-username/intentai/blob/main/CHANGELOG.md
Author-email: IntentAI Team <team@intentai.com>
Maintainer-email: IntentAI Team <team@intentai.com>
License: MIT
License-File: LICENSE
Keywords: ai,api,automation,cli,intent-detection,machine-learning,natural-language-processing,nlp,parameter-extraction,tool-calling
Classifier: Development Status :: 5 - Production/Stable
Classifier: Intended Audience :: Developers
Classifier: License :: OSI Approved :: MIT License
Classifier: Operating System :: OS Independent
Classifier: Programming Language :: Python :: 3
Classifier: Programming Language :: Python :: 3.8
Classifier: Programming Language :: Python :: 3.9
Classifier: Programming Language :: Python :: 3.10
Classifier: Programming Language :: Python :: 3.11
Classifier: Programming Language :: Python :: 3.12
Classifier: Topic :: Scientific/Engineering :: Artificial Intelligence
Classifier: Topic :: Software Development :: Libraries :: Application Frameworks
Classifier: Topic :: Software Development :: Libraries :: Python Modules
Classifier: Topic :: System :: Systems Administration
Classifier: Topic :: Text Processing :: Linguistic
Classifier: Topic :: Utilities
Requires-Python: >=3.8
Requires-Dist: pydantic>=2.0.0
Requires-Dist: typing-extensions>=4.0.0
Provides-Extra: dev
Requires-Dist: black>=23.0.0; extra == 'dev'
Requires-Dist: build>=1.0.0; extra == 'dev'
Requires-Dist: flake8>=6.0.0; extra == 'dev'
Requires-Dist: isort>=5.0.0; extra == 'dev'
Requires-Dist: mypy>=1.0.0; extra == 'dev'
Requires-Dist: pre-commit>=3.0.0; extra == 'dev'
Requires-Dist: pytest-cov>=4.0.0; extra == 'dev'
Requires-Dist: pytest>=7.0.0; extra == 'dev'
Requires-Dist: twine>=4.0.0; extra == 'dev'
Provides-Extra: docs
Requires-Dist: myst-parser>=2.0.0; extra == 'docs'
Requires-Dist: sphinx-rtd-theme>=1.0.0; extra == 'docs'
Requires-Dist: sphinx>=7.0.0; extra == 'docs'
Provides-Extra: test
Requires-Dist: pytest-cov>=4.0.0; extra == 'test'
Requires-Dist: pytest-mock>=3.0.0; extra == 'test'
Requires-Dist: pytest>=7.0.0; extra == 'test'
